uzbek_stopwords/__init__.py
uzbek_stopwords-0.0.1.dist-info/LICENSE
uzbek_stopwords-0.0.1.dist-info/METADATA
uzbek_stopwords-0.0.1.dist-info/WHEEL
uzbek_stopwords-0.0.1.dist-info/top_level.txt
uzbek_stopwords-0.0.1.dist-info/RECORD
